EasyDonate_Py/__init__.py
EasyDonate_Py/plugins.py
EasyDonate_Py/shop.py
easydonate_py-0.0.3.dist-info/METADATA
easydonate_py-0.0.3.dist-info/WHEEL
easydonate_py-0.0.3.dist-info/licenses/LICENSE.txt
easydonate_py-0.0.3.dist-info/RECORD
