Metadata-Version: 2.3
Name: EasyDonate-Py
Version: 0.0.3
Summary: Простая библиотека для взаимодействия с EasyDonate API
Project-URL: Homepage, https://github.com/TUUVCOME/easydonate-py
Project-URL: Issues, https://github.com/TUUVCOME/easydonate-py/issues
Author-email: refil <ru90671@gmail.com>, flizan <sushkov.code@yandex.com>
License-File: LICENSE.txt
Classifier: License :: OSI Approved :: MIT License
Classifier: Operating System :: OS Independent
Classifier: Programming Language :: Python :: 3
Requires-Python: >=3.10.0
